{"type": "productmeta", "data": [{"product_name": "CapCut", "topai_url": "https://topai.tools/t/capcut", "product_url": "https://capcut.com/?via=topaitools"}, {"product_name": "Veed.io", "topai_url": "https://topai.tools/t/veed-io", "product_url": "https://www.veed.io/avatars?via=topaitools"}, {"product_name": "VEED", "topai_url": "https://topai.tools/t/veed", "product_url": "https://www.veed.io/?via=topaitools"}, {"product_name": "InVideo", "topai_url": "https://topai.tools/t/invideo", "product_url": "https://invideo.io/make/add-text-to-video-online/?via=topaitools"}, {"product_name": "Wave.Video", "topai_url": "https://topai.tools/t/wave-video", "product_url": "https://wave.video/?via=topaitools"}, {"product_name": "Kapwing", "topai_url": "https://topai.tools/t/kapwing", "product_url": "https://kapwing.com/?via=topaitools"}, {"product_name": "Topaz Video AI", "topai_url": "https://topai.tools/t/topaz-video-ai", "product_url": "https://www.topazlabs.com/topaz-video-ai?via=topaitools"}, {"product_name": "Vmake Video Enhancer", "topai_url": "https://topai.tools/t/vmake-video-enhancer", "product_url": "https://vmake.ai/video-enhancer?via=topaitools"}, {"product_name": "Captions", "topai_url": "https://topai.tools/t/captions", "product_url": "https://www.captions.ai/?via=topaitools"}, {"product_name": "Vizard", "topai_url": "https://topai.tools/t/vizard", "product_url": "https://vizard.ai/?via=topaitools"}, {"product_name": "UniFab Video Enlarger AI", "topai_url": "https://topai.tools/t/unifab-video-enlarger-ai", "product_url": "https://www.dvdfab.cn/enlarger-ai.htm?via=topaitools"}, {"product_name": "Fineshare FineCam", "topai_url": "https://topai.tools/t/finecam", "product_url": "https://www.fineshare.com/finecam/?via=topaitools"}, {"product_name": "Unscreen.com", "topai_url": "https://topai.tools/t/unscreen-com", "product_url": "https://www.unscreen.com/?via=topaitools"}, {"product_name": "FocuSee", "topai_url": "https://topai.tools/t/focusee", "product_url": "https://gemoo.com/focusee?via=topaitools"}, {"product_name": "Apowersoft", "topai_url": "https://topai.tools/t/apowersoft", "product_url": "https://apowersoft.com/?via=topaitools"}, {"product_name": "Videoleap", "topai_url": "https://topai.tools/t/videoleap", "product_url": "https://www.videoleapapp.com/?via=topaitools"}, {"product_name": "SLICETUBE", "topai_url": "https://topai.tools/t/slicetube", "product_url": "https://www.slicetube.io/?via=topaitools"}, {"product_name": "InShot", "topai_url": "https://topai.tools/t/inshot", "product_url": "https://inshot.com/?via=topaitools"}, {"product_name": "Spikes Studio", "topai_url": "https://topai.tools/t/spikes-studio", "product_url": "https://spikes.studio/?via=topaitools"}, {"product_name": "Wisecut", "topai_url": "https://topai.tools/t/wisecut", "product_url": "https://www.wisecut.video/?via=topaitools"}, {"product_name": "Augie", "topai_url": "https://topai.tools/t/augie", "product_url": "https://meetaugie.com/?via=topaitools"}, {"product_name": "Qlip.ai", "topai_url": "https://topai.tools/t/qlip-ai", "product_url": "https://www.qlip.ai/?via=topaitools"}, {"product_name": "Scrip AI", "topai_url": "https://topai.tools/t/scrip-ai", "product_url": "https://scripai.com/?via=topaitools"}, {"product_name": "Zubtitle", "topai_url": "https://topai.tools/t/zubtitle", "product_url": "https://zubtitle.com/?via=topaitools"}, {"product_name": "Project Blink", "topai_url": "https://topai.tools/t/project-blink", "product_url": "https://labs.adobe.com/projects/blink/?via=topaitools"}, {"product_name": "SendShort", "topai_url": "https://topai.tools/t/sendshort", "product_url": "https://sendshort.ai/?via=topaitools"}, {"product_name": "Chopcast", "topai_url": "https://topai.tools/t/chopcast", "product_url": "https://chopcast.io/?via=topaitools"}, {"product_name": "Video Editor by Vidds", "topai_url": "https://topai.tools/t/video-editor-by-vidds", "product_url": "https://vidds.co/tools/online-video-editor/?via=topaitools"}, {"product_name": "Wannafake", "topai_url": "https://topai.tools/t/wannafake", "product_url": "https://wannafake.com/?via=topaitools"}, {"product_name": "QuickVid", "topai_url": "https://topai.tools/t/quickvid", "product_url": "https://www.quickvid.ai/?via=topaitools"}, {"product_name": "FireCut", "topai_url": "https://topai.tools/t/firecut", "product_url": "https://firecut.ai/?via=topaitools"}, {"product_name": "Gling", "topai_url": "https://topai.tools/t/gling", "product_url": "https://www.gling.ai/?via=topaitools"}, {"product_name": "KWIKmotion", "topai_url": "https://topai.tools/t/kwikmotion", "product_url": "https://www.kwikmotion.com/ai-cropping/en?via=topaitools"}, {"product_name": "Pixop", "topai_url": "https://topai.tools/t/pixop", "product_url": "https://www.pixop.com/?via=topaitools"}, {"product_name": "SubtitleBee", "topai_url": "https://topai.tools/t/subtitlebee", "product_url": "https://subtitlebee.com/?via=topaitools"}, {"product_name": "Detail.co", "topai_url": "https://topai.tools/t/detail-co", "product_url": "https://detail.co/?via=topaitools"}, {"product_name": "Perfectly Clear Video", "topai_url": "https://topai.tools/t/perfectly-clear-video", "product_url": "https://eyeq.photos/automatic-ai-video-enhancement/?via=topaitools"}, {"product_name": "AutoCut - Premiere Pro AI plugin", "topai_url": "https://topai.tools/t/autocut-premiere-pro-ai-plugin", "product_url": "https://www.autocut.fr/en/?via=topaitools"}, {"product_name": "Edit Videos Online", "topai_url": "https://topai.tools/t/edit-videos-online", "product_url": "https://edit-videos-online.com/?via=topaitools"}, {"product_name": "yuzzit.video", "topai_url": "https://topai.tools/t/yuzzit-video", "product_url": "https://yuzzit.video/?via=topaitools"}, {"product_name": "GoEnhance", "topai_url": "https://topai.tools/t/goenhance", "product_url": "https://www.goenhance.ai/?via=topaitools"}, {"product_name": "SubTitles.Love", "topai_url": "https://topai.tools/t/subtitles-love", "product_url": "https://subtitles.love/?via=topaitools"}, {"product_name": "Snapy.ai", "topai_url": "https://topai.tools/t/snapy-ai", "product_url": "https://snapy.ai/?via=topaitools"}, {"product_name": "Latte", "topai_url": "https://topai.tools/t/latte", "product_url": "https://latte.social/?via=topaitools"}, {"product_name": "Rizzle AI", "topai_url": "https://topai.tools/t/rizzle-ai", "product_url": "https://rizzle.com/?via=topaitools"}, {"product_name": "SmartEdit", "topai_url": "https://topai.tools/t/smartedit", "product_url": "https://smartedit.co/?via=topaitools"}, {"product_name": "Trimmr", "topai_url": "https://topai.tools/t/trimmr", "product_url": "https://www.trimmr.ai/app?via=topaitools"}, {"product_name": "HitPaw Video Object Remover", "topai_url": "https://topai.tools/t/hitpaw-video-object-remover", "product_url": "https://ixeau.com/ai-photo/?via=topaitools"}, {"product_name": "bigmp4", "topai_url": "https://topai.tools/t/bigmp4", "product_url": "https://bigmp4.com/?via=topaitools"}, {"product_name": "Big Room", "topai_url": "https://topai.tools/t/big-room", "product_url": "http://www.bigroom.tv/?via=topaitools"}, {"product_name": "vverse.ai", "topai_url": "https://topai.tools/t/vverse-ai", "product_url": "https://vverse.ai/?via=topaitools"}, {"product_name": "Free AI Video Upscaler", "topai_url": "https://topai.tools/t/free-ai-video-upscaler", "product_url": "https://free.upscaler.video/?via=topaitools"}, {"product_name": "Smili Media", "topai_url": "https://topai.tools/t/smili-media", "product_url": "https://www.smilimedia.com/?via=topaitools"}, {"product_name": "TopView.ai", "topai_url": "https://topai.tools/t/topview-ai", "product_url": "https://www.topview.ai/?via=topaitools"}, {"product_name": "Snapy", "topai_url": "https://topai.tools/t/snapy", "product_url": "https://www.videosilenceremover.com/?via=topaitools"}, {"product_name": "Imaginario AI", "topai_url": "https://topai.tools/t/imaginario-ai", "product_url": "https://www.imaginario.ai/?via=topaitools"}, {"product_name": "Bith.AI [Ghost]", "topai_url": "https://topai.tools/t/bith-ai-ghost", "product_url": "https://bith.ai/?via=topaitools"}, {"product_name": "Blur On", "topai_url": "https://topai.tools/t/blur-on", "product_url": "https://blur-on.com/en?via=topaitools"}, {"product_name": "Slick", "topai_url": "https://topai.tools/t/slick", "product_url": "https://slick.is/?via=topaitools"}, {"product_name": "FastCut", "topai_url": "https://topai.tools/t/fastcut", "product_url": "https://fastcutai.co/?via=topaitools"}, {"product_name": "Vocut", "topai_url": "https://topai.tools/t/vocut", "product_url": "https://www.vocut.com/?via=topaitools"}, {"product_name": "Banva", "topai_url": "https://topai.tools/t/banva", "product_url": "https://banva.io/?via=topaitools"}, {"product_name": "VoiceReplace", "topai_url": "https://topai.tools/t/voicereplace", "product_url": "https://www.voicereplace.app/?via=topaitools"}, {"product_name": "Edit on the Spot", "topai_url": "https://topai.tools/t/edit-on-the-spot", "product_url": "https://editonthespot.com/?via=topaitools"}, {"product_name": "AI Video Cut", "topai_url": "https://topai.tools/t/ai-video-cut", "product_url": "https://aivideocut.com/?via=topaitools"}, {"product_name": "Clippah", "topai_url": "https://topai.tools/t/clippah", "product_url": "https://www.clippah.co/?via=topaitools"}, {"product_name": "Type Studio", "topai_url": "https://topai.tools/t/type-studio", "product_url": "https://www.typestudio.co/tool/video-to-text/?via=topaitools"}, {"product_name": "Motionbear", "topai_url": "https://topai.tools/t/motionbear", "product_url": "https://motionbear.io/?via=topaitools"}, {"product_name": "PodCut", "topai_url": "https://topai.tools/t/podcut-io", "product_url": "https://podcut.io/?via=topaitools"}, {"product_name": "GhostCut", "topai_url": "https://topai.tools/t/ghostcut", "product_url": "https://ghostcut.jollytoday.com/?via=topaitools"}, {"product_name": "SubCap Genie", "topai_url": "https://topai.tools/t/subcap-genie", "product_url": "https://subcapgenie.com/?via=topaitools"}, {"product_name": "UniFab AI", "topai_url": "https://topai.tools/t/unifab-ai", "product_url": "https://unifab.ai/?via=topaitools"}, {"product_name": "LiveLink", "topai_url": "https://topai.tools/t/livelink", "product_url": "https://livelink.vip/?via=topaitools"}, {"product_name": "VidMaskPro", "topai_url": "https://topai.tools/t/vidmaskpro", "product_url": "https://www.vidmask.pro/?via=topaitools"}, {"product_name": "VideoPlus Studio", "topai_url": "https://topai.tools/t/videoplus-studio", "product_url": "https://videoplus.studio/?via=topaitools"}, {"product_name": "Million Dollar Edit", "topai_url": "https://topai.tools/t/million-dollar-edit-ai-video-editing", "product_url": "https://www.milliondollaredit.com/?via=topaitools"}, {"product_name": "Obiklip", "topai_url": "https://topai.tools/t/obiklip", "product_url": "https://obiklip.com/?via=topaitools"}, {"product_name": "Wondershare Uniconverter", "topai_url": "https://topai.tools/t/wondershare-uniconverter", "product_url": "https://videoconverter.wondershare.com/?via=topaitools"}, {"product_name": "AI Marvels - HitPaw", "topai_url": "https://topai.tools/t/ai-marvels-hitpaw", "product_url": "https://www.hitpaw.com/ai-photo-video-maker-app.html?via=topaitools"}, {"product_name": "Hitpaw Video Converter", "topai_url": "https://topai.tools/t/hitpaw-video-converter", "product_url": "https://www.hitpaw.com/video-converter.html?via=topaitools"}, {"product_name": "Wondershare Filmora", "topai_url": "https://topai.tools/t/wondershare-filmora", "product_url": "https://filmora.wondershare.com/?via=topaitools"}, {"product_name": "Clipfly", "topai_url": "https://topai.tools/t/clipfly", "product_url": "https://www.clipfly.ai/?via=topaitools"}, {"product_name": "HitPaw Edimakor", "topai_url": "https://topai.tools/t/hitpaw-edimakor", "product_url": "https://www.hitpaw.com/video-editor.html?via=topaitools"}, {"product_name": "HitPaw Video Enhancer", "topai_url": "https://topai.tools/t/hitpaw-video-enhancer", "product_url": "https://www.hitpaw.com/hitpaw-video-enhancer.html?via=topaitools"}, {"product_name": "HitPaw Online Video Enhancer", "topai_url": "https://topai.tools/t/hitpaw-online-video-enhancer", "product_url": "https://online.hitpaw.com/online-video-enhancer.html?via=topaitools"}, {"product_name": "Nova A.I.", "topai_url": "https://topai.tools/t/nova-a-i", "product_url": "https://wearenova.ai/?via=topaitools"}, {"product_name": "Vidio", "topai_url": "https://topai.tools/t/vidio", "product_url": "https://www.vidio.ai/tools/ai-video-editor?via=topaitools"}, {"product_name": "Video Editor AI", "topai_url": "https://topai.tools/t/video-editor-ai", "product_url": "https://videoeditorai.com/?via=topaitools"}, {"product_name": "EditAir", "topai_url": "https://topai.tools/t/editair", "product_url": "https://www.editair.app/?via=topaitools"}, {"product_name": "WrapUp", "topai_url": "https://topai.tools/t/wrapup", "product_url": "https://wrpup.com/?via=topaitools"}]}