{"type": "productmeta", "data": [{"product_name": "Sports AI.dev", "topai_url": "https://topai.tools/t/sports-ai-dev", "product_url": "https://www.sports-ai.dev/betting-bot?via=topaitools"}, {"product_name": "Ludex", "topai_url": "https://topai.tools/t/ludex", "product_url": "https://ludex.com/?via=topaitools"}, {"product_name": "Leans.ai", "topai_url": "https://topai.tools/t/leans-ai", "product_url": "https://leans.ai/ai-sports-betting/?via=topaitools"}, {"product_name": "Best Bike Split", "topai_url": "https://topai.tools/t/best-bike-split", "product_url": "https://bestbikesplit.com/?via=topaitools"}, {"product_name": "AI Sports Prediction", "topai_url": "https://topai.tools/t/ai-sports-prediction", "product_url": "https://sportsprediction.ai/?via=topaitools"}, {"product_name": "Soccersm Analytics AI", "topai_url": "https://topai.tools/t/soccersm-analytics-ai", "product_url": "https://soccersm.ai/?via=topaitools"}, {"product_name": "SafeBet", "topai_url": "https://topai.tools/t/safebet", "product_url": "https://safebet.ai/?via=topaitools"}, {"product_name": "Mysports.AI", "topai_url": "https://topai.tools/t/mysports-ai", "product_url": "https://mysports.ai/?via=topaitools"}, {"product_name": "Avais AI", "topai_url": "https://topai.tools/t/avais-ai", "product_url": "https://www.avais.ai/?via=topaitools"}, {"product_name": "footagentexam.com", "topai_url": "https://topai.tools/t/footagentexam-com", "product_url": "https://www.footagentexam.com/?via=topaitools"}, {"product_name": "MindGlimpse Sports", "topai_url": "https://topai.tools/t/mindglimpse-sports", "product_url": "https://mindglimpse.com/?via=topaitools"}, {"product_name": "Stat Pick AI", "topai_url": "https://topai.tools/t/stat-pick-ai", "product_url": "https://www.statpickai.com/?via=topaitools"}, {"product_name": "Smart Bracket", "topai_url": "https://topai.tools/t/smart-bracket", "product_url": "https://smartbracket.io/?via=topaitools"}, {"product_name": "HoopsGPT", "topai_url": "https://topai.tools/t/hoopsgpt", "product_url": "https://hoopsgpt.ai/?via=topaitools"}, {"product_name": "Apollo Co-Pilot Beta", "topai_url": "https://topai.tools/t/apollo-co-pilot-beta", "product_url": "https://www.apollo-copilot.com/?via=topaitools"}, {"product_name": "TENNI", "topai_url": "https://topai.tools/t/tenni", "product_url": "https://tenni.app/?via=topaitools"}, {"product_name": "Football AI", "topai_url": "https://topai.tools/t/football-ai", "product_url": "https://play.google.com/store/apps/details?id=com.footballscore.mobile?via=topaitools"}, {"product_name": "COPA", "topai_url": "https://topai.tools/t/copa", "product_url": "https://copascore.ai/?via=topaitools"}, {"product_name": "Locks", "topai_url": "https://topai.tools/t/locks", "product_url": "https://locks.gg/?via=topaitools"}, {"product_name": "Bracketwise", "topai_url": "https://topai.tools/t/bracketwise", "product_url": "https://bracketwise.app/?via=topaitools"}, {"product_name": "CatchThat", "topai_url": "https://topai.tools/t/catchthat", "product_url": "https://catchthat.io/?via=topaitools"}]}