{"type": "productmeta", "data": [{"product_name": "AI-Novel", "topai_url": "https://topai.tools/t/ai-novel", "product_url": "https://ai-novel.com/?via=topaitools"}, {"product_name": "NovelAI", "topai_url": "https://topai.tools/t/novelai", "product_url": "https://novelai.net/?via=topaitools"}, {"product_name": "Dreampress AI", "topai_url": "https://topai.tools/t/dreampress", "product_url": "https://www.dreampress.ai/?via=topaitools"}, {"product_name": "Artflow ai", "topai_url": "https://topai.tools/t/artflow-ai", "product_url": "https://artflow.ai/?via=topaitools"}, {"product_name": "Squibler", "topai_url": "https://topai.tools/t/squibler", "product_url": "https://www.squibler.io/?via=topaitools"}, {"product_name": "Datanumen - AI Story Generator", "topai_url": "https://topai.tools/t/datanumen-ai-story-generator", "product_url": "https://www.datanumen.com/ai-story-generator/?via=topaitools"}, {"product_name": "DreamGen", "topai_url": "https://topai.tools/t/dreamgen-role-play-story-writing", "product_url": "https://dreamgen.com/?via=topaitools"}, {"product_name": "DeepFiction AI", "topai_url": "https://topai.tools/t/deepfiction", "product_url": "https://www.deepfiction.ai/?via=topaitools"}, {"product_name": "Dreamily", "topai_url": "https://topai.tools/t/dreamily", "product_url": "https://dreamily.ai/?via=topaitools"}, {"product_name": "AIDungeon", "topai_url": "https://topai.tools/t/aidungeon", "product_url": "https://play.aidungeon.io/?via=topaitools"}, {"product_name": "StoryBooks", "topai_url": "https://topai.tools/t/storybooks", "product_url": "https://www.storybooks.app/?via=topaitools"}, {"product_name": "Mytales", "topai_url": "https://topai.tools/t/mytales", "product_url": "https://mytales.io/?via=topaitools"}, {"product_name": "Pirr", "topai_url": "https://topai.tools/t/pirr", "product_url": "https://www.pirr.me/?via=topaitools"}, {"product_name": "Deep Realms", "topai_url": "https://topai.tools/t/deep-realms", "product_url": "https://www.deeprealms.io/?via=topaitools"}, {"product_name": "BedtimeStory.ai", "topai_url": "https://topai.tools/t/bedtimestory-ai", "product_url": "https://bedtimestory.ai/?via=topaitools"}, {"product_name": "Fiction Fusion", "topai_url": "https://topai.tools/t/fiction-fusion", "product_url": "https://fictionfusion.io/?via=topaitools"}, {"product_name": "EndlessVN", "topai_url": "https://topai.tools/t/endlessvn", "product_url": "https://endlessvn.io/?via=topaitools"}, {"product_name": "Metos", "topai_url": "https://topai.tools/t/metos", "product_url": "https://www.metos.app/?via=topaitools"}, {"product_name": "InstaNovel", "topai_url": "https://topai.tools/t/instanovel", "product_url": "https://instanovel.ai/?via=topaitools"}, {"product_name": "Storytailor", "topai_url": "https://topai.tools/t/storytailor", "product_url": "https://www.storytailor.ai/?via=topaitools"}, {"product_name": "AI Personalized Children's Book", "topai_url": "https://topai.tools/t/ai-personalized-children-s-book", "product_url": "https://imajinn.ai/storybook/?via=topaitools"}, {"product_name": "We Made a Story", "topai_url": "https://topai.tools/t/we-made-a-story", "product_url": "https://www.wemadeastory.com/?via=topaitools"}, {"product_name": "Katalist AI", "topai_url": "https://topai.tools/t/katalist-ai", "product_url": "https://www.katalist.ai/?via=topaitools"}, {"product_name": "CreateBookAI", "topai_url": "https://topai.tools/t/createbookai", "product_url": "https://createbookai.com/?via=topaitools"}, {"product_name": "IMAGINaiTION", "topai_url": "https://topai.tools/t/imaginaition-ai", "product_url": "https://imaginaition.ai/?via=topaitools"}, {"product_name": "Life Story AI", "topai_url": "https://topai.tools/t/life-story-ai", "product_url": "https://life-story.ai/?via=topaitools"}, {"product_name": "Naria", "topai_url": "https://topai.tools/t/naria", "product_url": "https://naria.ai/?via=topaitools"}, {"product_name": "Story Path", "topai_url": "https://topai.tools/t/story-path", "product_url": "https://storypath.app/?via=topaitools"}, {"product_name": "StoriesForKids.ai: Personalized Kid's Books using AI", "topai_url": "https://topai.tools/t/storiesforkids-ai-personalized-kid-s-books-using-ai", "product_url": "https://www.storiesforkids.ai/?via=topaitools"}, {"product_name": "Fable Studio", "topai_url": "https://topai.tools/t/fable-studio", "product_url": "https://thefablestudio.co/?via=topaitools"}, {"product_name": "Subtxt", "topai_url": "https://topai.tools/t/subtxt", "product_url": "https://subtxt.app/?via=topaitools"}, {"product_name": "Tiny Pockets", "topai_url": "https://topai.tools/t/tiny-pockets", "product_url": "https://tinypockets.io/?via=topaitools"}, {"product_name": "FairyTailAI", "topai_url": "https://topai.tools/t/fairytailai", "product_url": "https://fairytailai.com/?via=topaitools"}, {"product_name": "Tell Me A Story", "topai_url": "https://topai.tools/t/tell-me-a-story", "product_url": "https://tellmeastoryai.app/?via=topaitools"}, {"product_name": "Artemis AI", "topai_url": "https://topai.tools/t/artemis-ai", "product_url": "https://artemisapp.ai/?via=topaitools"}, {"product_name": "My Wonder Tales", "topai_url": "https://topai.tools/t/my-wonder-tales", "product_url": "https://mywondertales.com/?via=topaitools"}, {"product_name": "Sprinkle", "topai_url": "https://topai.tools/t/sprinkle", "product_url": "https://getsprinkle.ch/?via=topaitools"}, {"product_name": "StoryGenerate.io", "topai_url": "https://topai.tools/t/storygenerate-io", "product_url": "https://storygenerate.io/?via=topaitools"}, {"product_name": "Fable Wizard", "topai_url": "https://topai.tools/t/fable-wizard", "product_url": "https://www.fablewizard.com/?via=topaitools"}, {"product_name": "Adventure Stories", "topai_url": "https://topai.tools/t/adventure-stories", "product_url": "https://www.adventurestories.ai/?via=topaitools"}, {"product_name": "WonderTales", "topai_url": "https://topai.tools/t/wondertales-bedtime-story-generator", "product_url": "https://wondertales.io/?via=topaitools"}, {"product_name": "Fabularis", "topai_url": "https://topai.tools/t/fabularis-art", "product_url": "https://fabularis.art/?via=topaitools"}, {"product_name": "Screenwriting.AI", "topai_url": "https://topai.tools/t/screenwriting-ai", "product_url": "https://screenwriting.ai/?via=topaitools"}, {"product_name": "StoryScape", "topai_url": "https://topai.tools/t/storyscape", "product_url": "https://storyscapeai.app/?via=topaitools"}, {"product_name": "AI Adventure", "topai_url": "https://topai.tools/t/ai-adventure", "product_url": "https://ai-adventure.steamship.com/?via=topaitools"}, {"product_name": "KidsAIStory", "topai_url": "https://topai.tools/t/kidsaistory", "product_url": "https://www.kidsaistory.com/?via=topaitools"}, {"product_name": "PicTales", "topai_url": "https://topai.tools/t/pictales", "product_url": "https://pictales.online/?via=topaitools"}, {"product_name": "HeartByte", "topai_url": "https://topai.tools/t/heartbyte", "product_url": "https://heartbyte.ai/?via=topaitools"}, {"product_name": "Legends", "topai_url": "https://topai.tools/t/legends", "product_url": "https://app.buildlegends.com/?via=topaitools"}, {"product_name": "WonderWeave", "topai_url": "https://topai.tools/t/wonderweave", "product_url": "https://www.wonderweave.app/?via=topaitools"}, {"product_name": "Maigic Book", "topai_url": "https://topai.tools/t/maigic-book", "product_url": "https://www.maigic.world/?via=topaitools"}, {"product_name": "Purrbook", "topai_url": "https://topai.tools/t/purrbook", "product_url": "https://apps.apple.com/us/app/purrbook-three-little-pigs/id6449464027?via=topaitools"}, {"product_name": "OvalOwl", "topai_url": "https://topai.tools/t/ovalowl", "product_url": "https://ovalowl.com/home.html?via=topaitools"}, {"product_name": "Beddy", "topai_url": "https://topai.tools/t/beddy", "product_url": "https://apps.apple.com/app/id6447703854?via=topaitools"}, {"product_name": "Erota", "topai_url": "https://topai.tools/t/erota", "product_url": "https://erota.app/?via=topaitools"}, {"product_name": "BabyStoryAI", "topai_url": "https://topai.tools/t/babystoryai", "product_url": "https://babystoryai.com/?via=topaitools"}, {"product_name": "Readingclub", "topai_url": "https://topai.tools/t/readingclub", "product_url": "https://www.readingclub.ai/?via=topaitools"}, {"product_name": "Morpheeus App", "topai_url": "https://topai.tools/t/morpheeus-app", "product_url": "https://www.morpheeus.com/?via=topaitools"}, {"product_name": "WizFairy", "topai_url": "https://topai.tools/t/wizfairy", "product_url": "https://wizfairy.com/?via=topaitools"}, {"product_name": "Dreamstories", "topai_url": "https://topai.tools/t/dreamstories", "product_url": "https://dreamstories.ai/?via=topaitools"}, {"product_name": "JoyPlanet", "topai_url": "https://topai.tools/t/joyplanet", "product_url": "https://www.joyplanet.store/?via=topaitools"}, {"product_name": "TMRA", "topai_url": "https://topai.tools/t/tmra", "product_url": "https://tmra.ai/?via=topaitools"}, {"product_name": "yourFable", "topai_url": "https://topai.tools/t/yourfable", "product_url": "https://yourfable.io/?via=topaitools"}, {"product_name": "Fireside", "topai_url": "https://topai.tools/t/fireside", "product_url": "https://www.fireside-story.com/?via=topaitools"}, {"product_name": "Wondertales.io", "topai_url": "https://topai.tools/t/wondertales-io", "product_url": "https://www.wondertales.io/?via=topaitools"}, {"product_name": "StoryDiffusion AI", "topai_url": "https://topai.tools/t/storydiffusion-ai", "product_url": "https://www.storydiffusion.org/?via=topaitools"}, {"product_name": "MemoryLane", "topai_url": "https://topai.tools/t/memorylane", "product_url": "https://memorylane.co/?via=topaitools"}, {"product_name": "FictionGPT", "topai_url": "https://topai.tools/t/fictiongpt", "product_url": "https://fictiongpt.xyz/?via=topaitools"}, {"product_name": "WhimsyWorks", "topai_url": "https://topai.tools/t/whimsyworks", "product_url": "https://whimsyapp.com/?via=topaitools"}, {"product_name": "SmartDreams", "topai_url": "https://topai.tools/t/smartdreams", "product_url": "https://smartdreams.ai/?via=topaitools"}, {"product_name": "StorySeed", "topai_url": "https://topai.tools/t/storyseed", "product_url": "https://koodup.com/journey/storyseed/?via=topaitools"}, {"product_name": "Tinytales", "topai_url": "https://topai.tools/t/tinytales", "product_url": "https://tiny-tales.app/?via=topaitools"}, {"product_name": "Make Tales", "topai_url": "https://topai.tools/t/make-tales", "product_url": "https://www.maketales.com/?via=topaitools"}, {"product_name": "Logolept", "topai_url": "https://topai.tools/t/logolept", "product_url": "https://logolept.com/?via=topaitools"}]}