{"type": "productmeta", "data": [{"product_name": "Bettertravel", "topai_url": "https://topai.tools/t/bettertravel", "product_url": "https://bettertravel.ai/?via=topaitools"}, {"product_name": "FreePlanTour", "topai_url": "https://topai.tools/t/freeplantour", "product_url": "https://freeplantour.com/?via=topaitools"}, {"product_name": "Guidie AI", "topai_url": "https://topai.tools/t/guidie-ai", "product_url": "https://syezdin.wixsite.com/guidie-ai?via=topaitools"}, {"product_name": "PlanTripAI", "topai_url": "https://topai.tools/t/plantripai", "product_url": "https://plantripai.com/?via=topaitools"}, {"product_name": "Travelities", "topai_url": "https://topai.tools/t/travelities", "product_url": "https://www.travelities.com/?via=topaitools"}, {"product_name": "Planit Earth", "topai_url": "https://topai.tools/t/planit-earth", "product_url": "https://planitearth.travel/?via=topaitools"}, {"product_name": "Wonderplan", "topai_url": "https://topai.tools/t/wonderplan", "product_url": "https://wonderplan.ai/?via=topaitools"}, {"product_name": "TRIPChatter AI", "topai_url": "https://topai.tools/t/tripchatter-travel-assistant", "product_url": "https://aiexplorerapp.com/?via=topaitools"}, {"product_name": "TraveLandz", "topai_url": "https://topai.tools/t/travellandz-com", "product_url": "https://travelandz.com/?via=topaitools"}, {"product_name": "Travelplan", "topai_url": "https://topai.tools/t/travelplan", "product_url": "https://www.travelplan-ai.com/?via=topaitools"}, {"product_name": "AItinerary", "topai_url": "https://topai.tools/t/aitinerary", "product_url": "https://www.aitinerary.ai/?via=topaitools"}, {"product_name": "Travelicious", "topai_url": "https://topai.tools/t/travelicious", "product_url": "https://www.travelicious.app/?via=topaitools"}, {"product_name": "The Trip Boutique", "topai_url": "https://topai.tools/t/the-trip-boutique", "product_url": "https://www.thetripboutique.co/business?via=topaitools"}, {"product_name": "My Travel Brain", "topai_url": "https://topai.tools/t/my-travel-brain", "product_url": "https://mytravelbrain.com/?via=topaitools"}, {"product_name": "Travopo", "topai_url": "https://topai.tools/t/travopo", "product_url": "https://travopo.com/?via=topaitools"}, {"product_name": "Tripplanner.ai", "topai_url": "https://topai.tools/t/tripplanner-ai", "product_url": "https://tripplanner.ai/?via=topaitools"}, {"product_name": "Summer AI", "topai_url": "https://topai.tools/t/summer-ai", "product_url": "https://apps.apple.com/us/app/summer-ai/id6447546296?via=topaitools"}, {"product_name": "JourneyPilot.ai", "topai_url": "https://topai.tools/t/journeypilot-ai", "product_url": "https://journeypilot.ai/?via=topaitools"}, {"product_name": "PlanTrip", "topai_url": "https://topai.tools/t/plantrip", "product_url": "https://plantrip.ai/?via=topaitools"}, {"product_name": "Tripper Guide", "topai_url": "https://topai.tools/t/tripper-guide", "product_url": "https://tripper.guide/?via=topaitools"}, {"product_name": "Traivl", "topai_url": "https://topai.tools/t/traivl", "product_url": "https://www.traivl.com/?via=topaitools"}, {"product_name": "TripClub", "topai_url": "https://topai.tools/t/trip-club", "product_url": "https://tripclub.ai/?via=topaitools"}, {"product_name": "YaatriAI by AasPass", "topai_url": "https://topai.tools/t/yaatriai-by-aaspass", "product_url": "https://www.aaspassapp.com/yaatriai?via=topaitools"}, {"product_name": "Travelnaut", "topai_url": "https://topai.tools/t/travelnaut", "product_url": "https://travelnaut.com/?via=topaitools"}, {"product_name": "Local Buddy", "topai_url": "https://topai.tools/t/local-buddy", "product_url": "https://www.localbuddy.info/?via=topaitools"}, {"product_name": "Travelmoji", "topai_url": "https://topai.tools/t/travelmoji", "product_url": "https://travelmoji.xyz/?via=topaitools"}, {"product_name": "Travel Echo", "topai_url": "https://topai.tools/t/travel-echo", "product_url": "https://travelecho.ai/?via=topaitools"}, {"product_name": "Vooyai", "topai_url": "https://topai.tools/t/vooyai", "product_url": "https://vooyai.com/?via=topaitools"}, {"product_name": "Plan My Trip ASAP", "topai_url": "https://topai.tools/t/plan-my-trip-asap", "product_url": "https://planmytripasap.com/?via=topaitools"}, {"product_name": "WhatDo.in", "topai_url": "https://topai.tools/t/whatdo-in", "product_url": "https://whatdo.in/?via=topaitools"}, {"product_name": "Itair", "topai_url": "https://topai.tools/t/itair", "product_url": "https://www.itair.io/?via=topaitools"}, {"product_name": "Roam Around", "topai_url": "https://topai.tools/t/roam-around", "product_url": "https://roamaround.app/?via=topaitools"}, {"product_name": "LowPriceTravels", "topai_url": "https://topai.tools/t/lowpricetravels", "product_url": "https://lowpricetravels.com/?via=topaitools"}, {"product_name": "Nomadspot", "topai_url": "https://topai.tools/t/nomadspot", "product_url": "https://nomadspot.me/?via=topaitools"}, {"product_name": "AI adventures", "topai_url": "https://topai.tools/t/ai-adventures", "product_url": "https://ai-adventures.com/?via=topaitools"}, {"product_name": "Copilot2trip.com", "topai_url": "https://topai.tools/t/copilot2trip-com", "product_url": "https://copilot2trip.com/?via=topaitools"}, {"product_name": "BabelOn", "topai_url": "https://topai.tools/t/babelon", "product_url": "https://babelontrip.com/?via=topaitools"}, {"product_name": "tripsei", "topai_url": "https://topai.tools/t/tripsei", "product_url": "https://tripsei.com/?via=topaitools"}, {"product_name": "planmytripnow.ai", "topai_url": "https://topai.tools/t/planmytripnow-ai", "product_url": "https://www.planmytripnow.ai/?via=topaitools"}, {"product_name": "TripTrio", "topai_url": "https://topai.tools/t/triptrio", "product_url": "https://triptrio.co/?via=topaitools"}, {"product_name": "bonMyVoyage", "topai_url": "https://topai.tools/t/bonmyvoyage", "product_url": "https://bonmyvoyage.com/?via=topaitools"}, {"product_name": "iPlan.ai", "topai_url": "https://topai.tools/t/iplan-ai", "product_url": "https://iplan.ai/?via=topaitools"}, {"product_name": "TripMate", "topai_url": "https://topai.tools/t/tripmate", "product_url": "http://tripmate.ai/?via=topaitools"}, {"product_name": "ForgetMyTrip", "topai_url": "https://topai.tools/t/forgetmytrip", "product_url": "https://www.forgemytrip.com/?via=topaitools"}, {"product_name": "Five Phrases", "topai_url": "https://topai.tools/t/five-phrases", "product_url": "https://www.fivephrasesapp.com/?via=topaitools"}, {"product_name": "JourneyPlan", "topai_url": "https://topai.tools/t/journeyplan", "product_url": "https://journeyplan.co/?via=topaitools"}, {"product_name": "Nowy", "topai_url": "https://topai.tools/t/nowy", "product_url": "https://nowy.io/?via=topaitools"}, {"product_name": "Journeai", "topai_url": "https://topai.tools/t/journeai", "product_url": "https://journeai.com/?via=topaitools"}, {"product_name": "Wanderias", "topai_url": "https://topai.tools/t/wanderias", "product_url": "https://www.wanderias.com/?via=topaitools"}, {"product_name": "AIreelity", "topai_url": "https://topai.tools/t/aireelity", "product_url": "https://www.aireelity.com/?via=topaitools"}, {"product_name": "Trava", "topai_url": "https://topai.tools/t/trava", "product_url": "https://wetrava.com/chat?via=topaitools"}, {"product_name": "Vacation & Travel Chat (GPT)", "topai_url": "https://topai.tools/t/vacation-travel-chat-gpt", "product_url": "https://www.usevacay.com/chatbot?via=topaitools"}, {"product_name": "TravelAroundTheWorld", "topai_url": "https://topai.tools/t/travelaroundtheworld", "product_url": "https://travelaroundtheworld.app/?via=topaitools"}, {"product_name": "Tripnotes.ai", "topai_url": "https://topai.tools/t/tripnotes-ai", "product_url": "https://tripnotes.ai/app?via=topaitools"}, {"product_name": "AI map", "topai_url": "https://topai.tools/t/ai-map", "product_url": "https://aimaps.app/?via=topaitools"}, {"product_name": "Orbt", "topai_url": "https://topai.tools/t/orbt", "product_url": "https://orbtapp.com/?via=topaitools"}, {"product_name": "SpeakSpots", "topai_url": "https://topai.tools/t/speakspots", "product_url": "https://speakspots.com/?via=topaitools"}, {"product_name": "AI Trip Planner", "topai_url": "https://topai.tools/t/ai-trip-planner", "product_url": "https://www.buildai.space/app/dae3da25-888e-448f-b15c-5a20ca4ca961?via=topaitools"}, {"product_name": "Travellergram", "topai_url": "https://topai.tools/t/travellergram", "product_url": "https://travellergram.com/?via=topaitools"}, {"product_name": "Triplay", "topai_url": "https://topai.tools/t/triplay", "product_url": "https://triplay.ai/?via=topaitools"}, {"product_name": "Explorerg - Discover", "topai_url": "https://topai.tools/t/explorerg-discover", "product_url": "https://www.explorerg.com/?via=topaitools"}, {"product_name": "Wanderbot", "topai_url": "https://topai.tools/t/wanderbot", "product_url": "https://wanderbot.io/?via=topaitools"}, {"product_name": "Wunderguide", "topai_url": "https://topai.tools/t/wunderguide", "product_url": "https://wunder.guide/?via=topaitools"}, {"product_name": "Travel Mate", "topai_url": "https://topai.tools/t/travel-mate", "product_url": "https://www.travel-mate.app/?via=topaitools"}, {"product_name": "WanderGenie", "topai_url": "https://topai.tools/t/wandergenie", "product_url": "https://www.wandergenie.app/?via=topaitools"}, {"product_name": "Her Trip Planner", "topai_url": "https://topai.tools/t/her-trip-planner", "product_url": "https://www.hertripplanner.ai/?via=topaitools"}, {"product_name": "Skoot", "topai_url": "https://topai.tools/t/skoot", "product_url": "https://skoothere.com/?via=topaitools"}, {"product_name": "AMBLR - AI Travel Planner", "topai_url": "https://topai.tools/t/amblr-ai-travel-planner", "product_url": "https://amblr.xyz/?via=topaitools"}, {"product_name": "TravAI", "topai_url": "https://topai.tools/t/travai", "product_url": "https://www.travai.co/?via=topaitools"}, {"product_name": "Mighty Travels", "topai_url": "https://topai.tools/t/mighty-travels", "product_url": "https://www.mightytravels.com/?via=topaitools"}]}