{"type": "productmeta", "data": [{"product_name": "Potions", "topai_url": "https://topai.tools/t/potions", "product_url": "https://get-potions.com/?via=topaitools"}, {"product_name": "Inventory365", "topai_url": "https://topai.tools/t/inventory365", "product_url": "https://inventory365.co/?via=topaitools"}, {"product_name": "assisty.ai", "topai_url": "https://topai.tools/t/assisty-ai", "product_url": "https://assisty.ai/?via=topaitools"}, {"product_name": "Aidaptive", "topai_url": "https://topai.tools/t/aidaptive", "product_url": "https://aidaptive.com/?via=topaitools"}, {"product_name": "Convictional", "topai_url": "https://topai.tools/t/convictional", "product_url": "https://convictional.com/?via=topaitools"}, {"product_name": "LEAFIO AI Retail", "topai_url": "https://topai.tools/t/leafio-ai-retail", "product_url": "https://leafio.ai/?via=topaitools"}, {"product_name": "Delineate", "topai_url": "https://topai.tools/t/delineate", "product_url": "https://www.delineate.co/?via=topaitools"}, {"product_name": "Scandilytics", "topai_url": "https://topai.tools/t/scandilytics", "product_url": "https://www.scandilytics.ai/?via=topaitools"}, {"product_name": "Saara.io", "topai_url": "https://topai.tools/t/saara.io", "product_url": "https://saara.io/?via=topaitools"}, {"product_name": "ConsumerAI", "topai_url": "https://topai.tools/t/consumerai", "product_url": "http://consumerai.deeprose.eu/?via=topaitools"}, {"product_name": "Data Analyst AI", "topai_url": "https://topai.tools/t/data-analyst-ai", "product_url": "https://www.scandilytics.ai/?via=topaitools"}, {"product_name": "crossingminds.com", "topai_url": "https://topai.tools/t/crossingminds-com", "product_url": "https://crossingminds.com/?via=topaitools"}, {"product_name": "Luigi's Box", "topai_url": "https://topai.tools/t/luigi-s-box", "product_url": "https://www.luigisbox.com/?via=topaitools"}, {"product_name": "CustomerIQ", "topai_url": "https://topai.tools/t/customeriq", "product_url": "https://www.getcustomeriq.com/?via=topaitools"}, {"product_name": "Outfits AI", "topai_url": "https://topai.tools/t/outfits-ai", "product_url": "https://www.outfitsai.com/?via=topaitools"}, {"product_name": "Manifest AI", "topai_url": "https://topai.tools/t/manifest-ai", "product_url": "https://getmanifest.ai/?via=topaitools"}, {"product_name": "Acobot", "topai_url": "https://topai.tools/t/acobot", "product_url": "https://acobot.ai/?via=topaitools"}, {"product_name": "XO Analytics", "topai_url": "https://topai.tools/t/xo-analytics", "product_url": "https://xo-analytics.com/?via=topaitools"}, {"product_name": "Shopifinity Engine\u2122", "topai_url": "https://topai.tools/t/shopifinity-enginetm", "product_url": "https://infinityaitools.com/?via=topaitools"}, {"product_name": "SoStocked", "topai_url": "https://topai.tools/t/sostocked", "product_url": "https://www.sostocked.com/?via=topaitools"}, {"product_name": "Standard Retail.", "topai_url": "https://topai.tools/t/standard-retail", "product_url": "https://standardretail.co/?via=topaitools"}, {"product_name": "AIShoppingAssistant", "topai_url": "https://topai.tools/t/aishoppingassistant", "product_url": "https://www.aishoppingassistant.net/?via=topaitools"}, {"product_name": "ComeHome", "topai_url": "https://topai.tools/t/comehome", "product_url": "https://www.comehome.ai/?via=topaitools"}, {"product_name": "Polar", "topai_url": "https://topai.tools/t/polar", "product_url": "https://polaranalytics.com/?via=topaitools"}, {"product_name": "MEJ ERP AI", "topai_url": "https://topai.tools/t/mej-erp-ai", "product_url": "https://mejerpai.com/?via=topaitools"}, {"product_name": "Covonyx", "topai_url": "https://topai.tools/t/covonyx", "product_url": "https://www.covonyx.com/?via=topaitools"}, {"product_name": "Out Of The Blue", "topai_url": "https://topai.tools/t/out-of-the-blue", "product_url": "https://outoftheblue.ai/?via=topaitools"}, {"product_name": "Clone My CEO", "topai_url": "https://topai.tools/t/clone-my-ceo", "product_url": "https://www.clonemyceo.com/?via=topaitools"}, {"product_name": "Skipped", "topai_url": "https://topai.tools/t/skipped", "product_url": "https://www.skipped.ai/?via=topaitools"}, {"product_name": "bodify.io", "topai_url": "https://topai.tools/t/bodify-io", "product_url": "https://www.bodify.io/?via=topaitools"}, {"product_name": "Incremental ai", "topai_url": "https://topai.tools/t/incremental-ai", "product_url": "https://incremental.com/?via=topaitools"}, {"product_name": "ShopMate", "topai_url": "https://topai.tools/t/shopmate", "product_url": "https://shopmateai.com/?via=topaitools"}, {"product_name": "IndexBox", "topai_url": "https://topai.tools/t/indexbox", "product_url": "https://indexbox.io/?via=topaitools"}, {"product_name": "retalon.com", "topai_url": "https://topai.tools/t/retalon-com", "product_url": "https://retalon.com/?via=topaitools"}, {"product_name": "GearChain", "topai_url": "https://topai.tools/t/gearchain", "product_url": "https://gearchain.io/?via=topaitools"}, {"product_name": "Innosearch AI - Shopping Assistant", "topai_url": "https://topai.tools/t/innosearch-ai-ai-powered-shopping-assistant", "product_url": "https://www.innosearch.ai/?via=topaitools"}, {"product_name": "Predict Expert AI", "topai_url": "https://topai.tools/t/predict-expert-ai", "product_url": "https://predict.expert/?via=topaitools"}, {"product_name": "Sku Fetch", "topai_url": "https://topai.tools/t/sku-fetch", "product_url": "https://skufetch.com/?via=topaitools"}, {"product_name": "Topzeal", "topai_url": "https://topai.tools/t/topzeal", "product_url": "https://topzeal.com/?via=topaitools"}, {"product_name": "Reform", "topai_url": "https://topai.tools/t/reformhq", "product_url": "https://www.reformhq.com/?via=topaitools"}, {"product_name": "Demand Forecast", "topai_url": "https://topai.tools/t/demand-forecast", "product_url": "https://supplychaintelligent.gumroad.com/l/forecast?via=topaitools"}, {"product_name": "secretsaucepartners.com", "topai_url": "https://topai.tools/t/secretsaucepartners-com", "product_url": "https://secretsaucepartners.com/?via=topaitools"}, {"product_name": "Recommendix", "topai_url": "https://topai.tools/t/recommendix", "product_url": "https://recommendix.com/?via=topaitools"}, {"product_name": "Enalito 2.0", "topai_url": "https://topai.tools/t/enalito-2-0", "product_url": "https://enalito.com/?via=topaitools"}, {"product_name": "Your eCom Agent", "topai_url": "https://topai.tools/t/your-ecom-agent", "product_url": "https://www.yourecomagent.com/?via=topaitools"}, {"product_name": "Logistify AI", "topai_url": "https://topai.tools/t/logistify-ai", "product_url": "https://www.logistify.ai/?via=topaitools"}, {"product_name": "AskMetric", "topai_url": "https://topai.tools/t/askmetric", "product_url": "https://www.askmetric.com/?via=topaitools"}, {"product_name": "Buysmart", "topai_url": "https://topai.tools/t/buysmart", "product_url": "https://buysmart.ai/?via=topaitools"}, {"product_name": "bythenumbersapp.com", "topai_url": "https://topai.tools/t/bythenumbersapp-com", "product_url": "https://bythenumbersapp.com/?via=topaitools"}, {"product_name": "5-Out", "topai_url": "https://topai.tools/t/5-out", "product_url": "https://www.5out.io/?via=topaitools"}, {"product_name": "Siesta", "topai_url": "https://topai.tools/t/siesta", "product_url": "https://siestaguides.com/?via=topaitools"}, {"product_name": "V-retail", "topai_url": "https://topai.tools/t/v-retail", "product_url": "https://www.vretail.space/?via=topaitools"}, {"product_name": "inspectorio.com", "topai_url": "https://topai.tools/t/inspectorio-com", "product_url": "https://inspectorio.com/?via=topaitools"}, {"product_name": "Glass", "topai_url": "https://topai.tools/t/glass", "product_url": "https://getglass.co/?via=topaitools"}, {"product_name": "Shopmate Chat", "topai_url": "https://topai.tools/t/shopmate-chat", "product_url": "https://www.shopmate.chat/?via=topaitools"}, {"product_name": "Octocom", "topai_url": "https://topai.tools/t/octocom", "product_url": "https://www.octocom.ai/?via=topaitools"}, {"product_name": "ChatKPI", "topai_url": "https://topai.tools/t/chatkpi", "product_url": "https://www.chatkpi.co/?via=topaitools"}, {"product_name": "Brightflow AI", "topai_url": "https://topai.tools/t/brightflow-ai", "product_url": "https://brightflow.ai/?via=topaitools"}, {"product_name": "Productscope.AI", "topai_url": "https://topai.tools/t/productscope-ai", "product_url": "https://productscope.ai/?via=topaitools"}, {"product_name": "SaaS Library", "topai_url": "https://topai.tools/t/saas-library", "product_url": "https://www.saaslibrary.dev/?via=topaitools"}, {"product_name": "Intellimize", "topai_url": "https://topai.tools/t/intellimize", "product_url": "https://www.intellimize.com/?via=topaitools"}, {"product_name": "AI Puzzles", "topai_url": "https://topai.tools/t/ai-puzzles", "product_url": "https://aipuzzle.myshopify.com/?via=topaitools"}, {"product_name": "Athenic AI", "topai_url": "https://topai.tools/t/athenic-ai", "product_url": "https://www.athenic.com/?via=topaitools"}, {"product_name": "AI Store Manager", "topai_url": "https://topai.tools/t/ai-store-manager", "product_url": "https://aistoremanager.com/?via=topaitools"}, {"product_name": "Salesforge", "topai_url": "https://topai.tools/t/salesforge", "product_url": "https://salesforge.ai/?via=topaitools"}, {"product_name": "Yepp", "topai_url": "https://topai.tools/t/yepp", "product_url": "https://www.yepp.ai/?via=topaitools"}, {"product_name": "E-Procure AI", "topai_url": "https://topai.tools/t/e-procure-ai", "product_url": "https://www.e-procureai.com/?via=topaitools"}, {"product_name": "M1-project", "topai_url": "https://topai.tools/t/m1-project", "product_url": "https://m1-project.com/?via=topaitools"}]}