{"type": "productmeta", "data": [{"product_name": "Clearmind", "topai_url": "https://topai.tools/t/clearmind", "product_url": "https://www.clearmind.plus/?via=topaitools"}, {"product_name": "Space of mind", "topai_url": "https://topai.tools/t/space-of-mind", "product_url": "https://www.spaceofmind.com/?via=topaitools"}, {"product_name": "Stamina AI", "topai_url": "https://topai.tools/t/stamina-ai", "product_url": "https://www.stamina.chat/?via=topaitools"}, {"product_name": "FriendnPal", "topai_url": "https://topai.tools/t/friendnpal", "product_url": "https://friendnpal.com/?via=topaitools"}, {"product_name": "mindbuddy app", "topai_url": "https://topai.tools/t/mindbuddy-app", "product_url": "https://mindbuddy.io/?via=topaitools"}, {"product_name": "Anyo", "topai_url": "https://topai.tools/t/anyo", "product_url": "https://anyo.co/app?via=topaitools"}, {"product_name": "CalmMind", "topai_url": "https://topai.tools/t/calmmind", "product_url": "https://calmmind.ai/?via=topaitools"}, {"product_name": "Well Me Right", "topai_url": "https://topai.tools/t/well-me-right", "product_url": "https://www.wellmeright.com/?via=topaitools"}, {"product_name": "Aidacura", "topai_url": "https://topai.tools/t/aidacura", "product_url": "https://aidacura.com/?via=topaitools"}, {"product_name": "Vital", "topai_url": "https://topai.tools/t/vital", "product_url": "https://joinvital.ai/?via=topaitools"}, {"product_name": "Flourish", "topai_url": "https://topai.tools/t/flourish", "product_url": "https://www.flourishtech.app/?via=topaitools"}, {"product_name": "calmify.ai", "topai_url": "https://topai.tools/t/calmify-ai", "product_url": "https://www.calmify.ai/?via=topaitools"}, {"product_name": "Deepen", "topai_url": "https://topai.tools/t/deepen", "product_url": "https://thedeepen.app/?via=topaitools"}, {"product_name": "LeapLife", "topai_url": "https://topai.tools/t/leaplife", "product_url": "https://leaplife.app/?via=topaitools"}, {"product_name": "HeartDialog", "topai_url": "https://topai.tools/t/heartdialog", "product_url": "https://heartdialog.com/?via=topaitools"}, {"product_name": "MindwellAI", "topai_url": "https://topai.tools/t/mindwellai", "product_url": "https://mindwell.ai/?via=topaitools"}, {"product_name": "Inner Lighthouse", "topai_url": "https://topai.tools/t/inner-lighthouse", "product_url": "https://www.innerlighthouseapp.com/?via=topaitools"}, {"product_name": "Ponder", "topai_url": "https://topai.tools/t/ponder", "product_url": "https://www.useponder.app/?via=topaitools"}, {"product_name": "FindYourTriggers", "topai_url": "https://topai.tools/t/findyourtriggers", "product_url": "https://findyourtriggers.com/?via=topaitools"}, {"product_name": "Balm.ai", "topai_url": "https://topai.tools/t/balm-ai", "product_url": "https://www.balm.ai/?via=topaitools"}, {"product_name": "Mood AI by Mindset", "topai_url": "https://topai.tools/t/mood-ai-by-mindset", "product_url": "https://www.getmindset.com/?via=topaitools"}, {"product_name": "iprevail.com", "topai_url": "https://topai.tools/t/iprevail-com", "product_url": "https://iprevail.com/?via=topaitools"}, {"product_name": "Quokka!", "topai_url": "https://topai.tools/t/quokka", "product_url": "https://www.quokka-ai.com/?via=topaitools"}, {"product_name": "MoodPen", "topai_url": "https://topai.tools/t/moodpen", "product_url": "https://moodpen.com/?via=topaitools"}, {"product_name": "Lotus", "topai_url": "https://topai.tools/t/lotus-the-online-therapist", "product_url": "https://lotustherapist.com/?via=topaitools"}, {"product_name": "Strangify", "topai_url": "https://topai.tools/t/strangify", "product_url": "https://strangify.com/?via=topaitools"}, {"product_name": "Sensae Loop", "topai_url": "https://topai.tools/t/sensae-loop", "product_url": "https://www.sensae.com/?via=topaitools"}, {"product_name": "AMARI", "topai_url": "https://topai.tools/t/amari", "product_url": "https://thebrocode.carrd.co/?via=topaitools"}, {"product_name": "therapini", "topai_url": "https://topai.tools/t/therapini", "product_url": "https://therapini.com/?via=topaitools"}, {"product_name": "Bobby Chat", "topai_url": "https://topai.tools/t/bobby-chat", "product_url": "https://www.bobby-chat.com/?via=topaitools"}, {"product_name": "Mindsum", "topai_url": "https://topai.tools/t/mindsum", "product_url": "https://www.mindsum.app/chatbot?via=topaitools"}, {"product_name": "Heartfelt Services", "topai_url": "https://topai.tools/t/heartfelt-services", "product_url": "https://heartfelt.services/?via=topaitools"}, {"product_name": "AI Hypnosis App", "topai_url": "https://topai.tools/t/ai-hypnosis-app", "product_url": "https://www.aihypnosisapp.com/?via=topaitools"}, {"product_name": "BodyGuru", "topai_url": "https://topai.tools/t/bodyguru", "product_url": "https://www.bodyguru.ai/?via=topaitools"}, {"product_name": "LeeAI", "topai_url": "https://topai.tools/t/leeai", "product_url": "https://www.lee-ai.com/?via=topaitools"}, {"product_name": "Neomind", "topai_url": "https://topai.tools/t/neomind", "product_url": "https://neomind.app/?via=topaitools"}, {"product_name": "6000 thoughts", "topai_url": "https://topai.tools/t/6000-thoughts", "product_url": "https://6000thoughts.com/?via=topaitools"}, {"product_name": "Drsaam", "topai_url": "https://topai.tools/t/drsaam", "product_url": "https://drsaam.me/?via=topaitools"}, {"product_name": "Dr. FeelGood", "topai_url": "https://topai.tools/t/dr-feelgood", "product_url": "https://drfeelgood.coach/?via=topaitools"}, {"product_name": "FeelGood", "topai_url": "https://topai.tools/t/feelgood", "product_url": "https://www.buildai.space/app/feel-good-app?via=topaitools"}, {"product_name": "Cara", "topai_url": "https://topai.tools/t/cara", "product_url": "https://www.messagecara.app/?via=topaitools"}, {"product_name": "Lily", "topai_url": "https://topai.tools/t/lily", "product_url": "https://www.meetlily.ai/?via=topaitools"}, {"product_name": "Therapy with AI", "topai_url": "https://topai.tools/t/free-ai-therapist", "product_url": "https://therapywithai.com/?via=topaitools"}, {"product_name": "Yuna AI", "topai_url": "https://topai.tools/t/yuna-ai", "product_url": "https://yuna.io/?via=topaitools"}, {"product_name": "Shoorah Wellbeing", "topai_url": "https://topai.tools/t/shoorah-wellbeing", "product_url": "https://shoorah.io/?via=topaitools"}, {"product_name": "Insightful", "topai_url": "https://topai.tools/t/insightful", "product_url": "https://insightful.page/?via=topaitools"}, {"product_name": "Seren", "topai_url": "https://topai.tools/t/seren", "product_url": "https://goseren.com/?via=topaitools"}, {"product_name": "MindForest", "topai_url": "https://topai.tools/t/mindforest", "product_url": "https://mindforest.ai/?via=topaitools"}, {"product_name": "Balance", "topai_url": "https://topai.tools/t/balance", "product_url": "https://balance.dvy.io/?via=topaitools"}, {"product_name": "Buddiz", "topai_url": "https://topai.tools/t/buddiz", "product_url": "https://www.buddiz.ai/?via=topaitools"}, {"product_name": "AtFirst", "topai_url": "https://topai.tools/t/atfirst", "product_url": "https://apps.apple.com/app/atfirst-daily-affirmations/id6451104136?via=topaitools"}, {"product_name": "PinkPiko", "topai_url": "https://topai.tools/t/pinkpiko", "product_url": "https://www.pinkpiko.com/?via=topaitools"}, {"product_name": "Pink Piko", "topai_url": "https://topai.tools/t/pink-piko-ai-emotion-journal", "product_url": "https://www.pinkpiko.com/?via=topaitools"}, {"product_name": "Meditator.pro", "topai_url": "https://topai.tools/t/meditator-pro", "product_url": "https://www.meditator.pro/?via=topaitools"}, {"product_name": "Call an AI", "topai_url": "https://topai.tools/t/call-an-ai", "product_url": "https://callanai.com/?via=topaitools"}, {"product_name": "Soula Care", "topai_url": "https://topai.tools/t/soula-care", "product_url": "https://soula.care/?via=topaitools"}, {"product_name": "Reassurance AI (Beta)", "topai_url": "https://topai.tools/t/reassurance-ai-beta", "product_url": "https://reassurance.ai/?via=topaitools"}, {"product_name": "Mindsera", "topai_url": "https://topai.tools/t/mindsera", "product_url": "https://www.mindsera.com/?via=topaitools"}, {"product_name": "Selftalk.ing", "topai_url": "https://topai.tools/t/selftalk-ing", "product_url": "https://www.selftalk.ing/?via=topaitools"}, {"product_name": "Vibly", "topai_url": "https://topai.tools/t/vibly", "product_url": "https://vibly.io/?via=topaitools"}, {"product_name": "Woebot Health", "topai_url": "https://topai.tools/t/woebot-health", "product_url": "https://woebothealth.com/?via=topaitools"}, {"product_name": "Cerebral Ai", "topai_url": "https://topai.tools/t/cerebral-ai", "product_url": "https://www.cerebralai.studio/?via=topaitools"}, {"product_name": "Insight Journal", "topai_url": "https://topai.tools/t/insight-journal", "product_url": "https://www.insightjournal.ai/?via=topaitools"}, {"product_name": "Reassurance", "topai_url": "https://topai.tools/t/reassurance", "product_url": "https://reassurance.ai/?via=topaitools"}, {"product_name": "Momentary", "topai_url": "https://topai.tools/t/momentary", "product_url": "https://momentary.cc/?via=topaitools"}, {"product_name": "Rosebud", "topai_url": "https://topai.tools/t/rosebud-ai", "product_url": "https://rosebud.app/?via=topaitools"}, {"product_name": "Neurture", "topai_url": "https://topai.tools/t/neurture", "product_url": "https://neurtureapp.com/?via=topaitools"}, {"product_name": "Pneuma", "topai_url": "https://topai.tools/t/pneuma", "product_url": "https://www.pneuma-app.com/?via=topaitools"}, {"product_name": "Ultra-Attention", "topai_url": "https://topai.tools/t/ultra-attention", "product_url": "https://ultra-attention.com/?via=topaitools"}, {"product_name": "DayBright: Daily Inspiration", "topai_url": "https://topai.tools/t/daybright-daily-inspiration", "product_url": "https://daybright.us/?via=topaitools"}]}