{"product_summary": "Although I haven't provided the actual text from the website, I can help you structure the JSON object as per your request. Please provide the necessary information, and I'll be happy to generate the JSON for you.", "product_categories": [], "product_pros": [], "product_cons": [], "product_usecases": [], "product_toolfor": [], "product_pricing": [], "product_rating": null, "product_name": "Skills Over Paper", "product_unique_id": "00a32f87-d07e-460f-aee9-1968568bd4dd", "product_pricing_available": null, "product_affiliate_available": null, "product_url": "https://www.skillsoverpaper.com"}