{"product_summary": "SongR is a groundbreaking AI-powered tool that revolutionizes song creation. With just a few clicks, users can generate fully customized songs with unique lyrics, vocals, and accompaniments. Whether you're a musician, content creator, or simply someone who loves music, SongR empowers you to create and share your own personalized songs effortlessly.", "product_categories": ["Music Production", "AI-Powered Tools", "Songwriting Tools", "Content Creation Tools", "Personalized Gift Ideas"], "product_pros": ["Effortless song creation with minimal musical experience", "Generates unique lyrics based on your input", "Adds vocals and accompaniments from various genres", "Enables sharing of songs on social media", "Perfect for creating engaging content, entertaining loved ones, and sending meaningful song gifts"], "product_cons": ["May require some experimentation to achieve desired results", "Lack of advanced editing features for fine-tuning songs", "Limited customization options for certain elements of the song", "Potential for repetitive lyrics if input keywords are not specific enough", "May not suit professional musicians seeking complete control over their creations"], "product_usecases": [{"case": "Content Marketing", "details": "Create unique and engaging audio content for podcasts, videos, and social media campaigns."}, {"case": "Personalized Gifts", "details": "Surprise loved ones with heartfelt and unforgettable song gifts for special occasions."}, {"case": "Educational", "details": "Use SongR in educational settings to teach students about music theory, songwriting, and creativity."}, {"case": "Language Learning", "details": "Immerse yourself in different languages by generating songs with lyrics in your target language."}, {"case": "Musical Expression", "details": "Express your creativity and share your musical ideas with others through personalized songs."}], "product_toolfor": [{"target": "Musicians", "details": "Create demos, experiment with new genres, and quickly generate song ideas."}, {"target": "Content Creators", "details": "Enhance videos, podcasts, and other content with custom music."}, {"target": "Individuals", "details": "Express themselves musically, create personalized gifts, and engage with others through music."}, {"target": "Educators", "details": "Make learning interactive and engaging by incorporating music into lessons."}, {"target": "Businesses", "details": "Create unique audio branding, marketing materials, and employee engagement initiatives."}], "product_pricing": "Pricing information is not available on the provided text.", "product_rating": "8/10", "product_name": "SongR", "product_unique_id": "025aa7a1-0fc3-4e16-bf6f-47ce1410dc05", "product_pricing_available": null, "product_affiliate_available": null, "product_url": "https://www.songr.ai"}